dna_features_viewer/GraphicFeature.py
dna_features_viewer/__init__.py
dna_features_viewer/biotools.py
dna_features_viewer/compute_features_levels.py
dna_features_viewer/version.py
dna_features_viewer/BiopythonTranslator/BiopythonTranslator.py
dna_features_viewer/BiopythonTranslator/BiopythonTranslatorBase.py
dna_features_viewer/BiopythonTranslator/BlackBoxlessLabelTranslator.py
dna_features_viewer/BiopythonTranslator/__init__.py
dna_features_viewer/CircularGraphicRecord/ArrowWedge.py
dna_features_viewer/CircularGraphicRecord/CircularGraphicRecord.py
dna_features_viewer/CircularGraphicRecord/__init__.py
dna_features_viewer/GraphicRecord/BokehPlottableMixin.py
dna_features_viewer/GraphicRecord/GraphicRecord.py
dna_features_viewer/GraphicRecord/MatplotlibPlottableMixin.py
dna_features_viewer/GraphicRecord/MultilinePlottableMixin.py
dna_features_viewer/GraphicRecord/SequenceAndTranslationMixin.py
dna_features_viewer/GraphicRecord/__init__.py
dna_features_viewer_lite-3.1.5.1.dist-info/licenses/LICENSE
dna_features_viewer_lite-3.1.5.1.dist-info/METADATA
dna_features_viewer_lite-3.1.5.1.dist-info/WHEEL
dna_features_viewer_lite-3.1.5.1.dist-info/top_level.txt
dna_features_viewer_lite-3.1.5.1.dist-info/RECORD
