Metadata-Version: 2.4
Name: dna_features_viewer_lite
Version: 3.1.5.1
Summary: Plot features from DNA sequences (e.g. Genbank) with Python
Author: Zulko
License-Expression: MIT
Project-URL: Homepage, https://github.com/Edinburgh-Genome-Foundry/DnaFeaturesViewer
Keywords: DNA,Sequence,Feature,Genbank,Biopython,Matplotlib
License-File: LICENSE
Requires-Dist: matplotlib>=3
Requires-Dist: packaging
Dynamic: license-file
